{
  "match_info": {
    "date": "2022-08-28",
    "home_score": 0,
    "away_score": 1,
    "attendance": 41796,
    "referee": "David Coote",
    "venue": "Villa Park, Birmingham"
  },
  "home_team": {
    "name": "Aston Villa",
    "fbref_id": "8602292d",
    "manager": "Steven Gerrard",
    "captain": "John McGinn"
  },
  "away_team": {
    "name": "West Ham United",
    "fbref_id": "7c21e445",
    "manager": "David Moyes",
    "captain": "Declan Rice"
  },
  "lineups": {
    "home": {
      "starting_xi": [
        {
          "name": "Ollie Watkins",
          "fbref_id": "aed3a70f",
          "position": "FW",
          "jersey_number": 11
        },
        {
          "name": "Boubacar Kamara",
          "fbref_id": "cc77354e",
          "position": "CM,DM",
          "jersey_number": 44
        },
        {
          "name": "Lucas Digne",
          "fbref_id": "1b84dbe1",
          "position": "LB",
          "jersey_number": 27
        },
        {
          "name": "Calum Chambers",
          "fbref_id": "dc6f5bdd",
          "position": "CB",
          "jersey_number": 16
        },
        {
          "name": "Ezri Konsa",
          "fbref_id": "0313a347",
          "position": "CB",
          "jersey_number": 4
        },
        {
          "name": "Matty Cash",
          "fbref_id": "2389cdc2",
          "position": "RB",
          "jersey_number": 2
        },
        {
          "name": "Emiliano Martínez",
          "fbref_id": "7956236f",
          "position": "GK",
          "jersey_number": 1
        },
        {
          "name": "John McGinn",
          "fbref_id": "90f91999",
          "position": "LM",
          "jersey_number": 7
        },
        {
          "name": "Danny Ings",
          "fbref_id": "07802f7f",
          "position": "FW",
          "jersey_number": 9
        },
        {
          "name": "Philippe Coutinho",
          "fbref_id": "0ef89a37",
          "position": "AM",
          "jersey_number": 23
        },
        {
          "name": "Douglas Luiz",
          "fbref_id": "6f7d826d",
          "position": "RM",
          "jersey_number": 6
        }
      ],
      "substitutes": [
        {
          "name": "Robin Olsen",
          "fbref_id": "e7ee38c3",
          "position": null,
          "jersey_number": null
        },
        {
          "name": "Emi Buendía",
          "fbref_id": "66b76d44",
          "position": "AM",
          "jersey_number": 10
        },
        {
          "name": "Ludwig Augustinsson",
          "fbref_id": "9fec8860",
          "position": null,
          "jersey_number": null
        },
        {
          "name": "Ashley Young",
          "fbref_id": "be927d03",
          "position": null,
          "jersey_number": null
        },
        {
          "name": "Marvelous Nakamba",
          "fbref_id": "de5b5570",
          "position": null,
          "jersey_number": null
        },
        {
          "name": "Leon Bailey",
          "fbref_id": "3a233281",
          "position": "FW,RW",
          "jersey_number": 31
        },
        {
          "name": "Cameron Archer",
          "fbref_id": "05e8ca6d",
          "position": "DM",
          "jersey_number": 35
        },
        {
          "name": "Jacob Ramsey",
          "fbref_id": "1544f145",
          "position": "RM,LW",
          "jersey_number": 41
        },
        {
          "name": "Tim Iroegbunam",
          "fbref_id": "84c5ceea",
          "position": null,
          "jersey_number": null
        }
      ],
      "formation": null
    },
    "away": {
      "starting_xi": [
        {
          "name": "Jarrod Bowen",
          "fbref_id": "79c84d1c",
          "position": "FW,RW",
          "jersey_number": 20
        },
        {
          "name": "Pablo Fornals",
          "fbref_id": "82927de4",
          "position": "CM,LM",
          "jersey_number": 8
        },
        {
          "name": "Declan Rice",
          "fbref_id": "1c7012b8",
          "position": "CM",
          "jersey_number": 41
        },
        {
          "name": "Tomáš Souček",
          "fbref_id": "6613c819",
          "position": "CM,RM",
          "jersey_number": 28
        },
        {
          "name": "Aaron Cresswell",
          "fbref_id": "4f974391",
          "position": "CB,LB",
          "jersey_number": 3
        },
        {
          "name": "Kurt Zouma",
          "fbref_id": "ce4246f5",
          "position": "CB",
          "jersey_number": 4
        },
        {
          "name": "Thilo Kehrer",
          "fbref_id": "51dbeea9",
          "position": "CB",
          "jersey_number": 24
        },
        {
          "name": "Łukasz Fabiański",
          "fbref_id": "9328b835",
          "position": "GK",
          "jersey_number": 1
        },
        {
          "name": "Vladimír Coufal",
          "fbref_id": "fdf3cb77",
          "position": "WB,RB",
          "jersey_number": 5
        },
        {
          "name": "Gianluca Scamacca",
          "fbref_id": "8790f988",
          "position": "FW",
          "jersey_number": 7
        },
        {
          "name": "Emerson Palmieri",
          "fbref_id": "e0bc6fdc",
          "position": "WB",
          "jersey_number": 33
        }
      ],
      "substitutes": [
        {
          "name": "Alphonse Areola",
          "fbref_id": "2f965a72",
          "position": null,
          "jersey_number": 3
        },
        {
          "name": "Michail Antonio",
          "fbref_id": "ac05f970",
          "position": "FW",
          "jersey_number": 9
        },
        {
          "name": "Saïd Benrahma",
          "fbref_id": "5a04fd92",
          "position": "LW,WB",
          "jersey_number": 22
        },
        {
          "name": "Ben Johnson",
          "fbref_id": "9319781b",
          "position": "WB",
          "jersey_number": 2
        }
      ],
      "formation": null
    }
  },
  "events": {
    "goals": [
      {
        "type": "goal",
        "player_name": "Pablo Fornals",
        "player_id": "82927de4",
        "minute": "74",
        "team": "away",
        "assist_player": "Declan Rice",
        "assist_player_id": "1c7012b8"
      }
    ],
    "assists": [
      {
        "type": "assist",
        "player_name": "Declan Rice",
        "player_id": "1c7012b8",
        "minute": "74",
        "team": "away"
      }
    ],
    "cards": [
      {
        "type": "card",
        "card_type": "yellow",
        "player_name": "Matty Cash",
        "player_id": "2389cdc2",
        "minute": "57",
        "team": "home"
      },
      {
        "type": "card",
        "card_type": "yellow",
        "player_name": "Boubacar Kamara",
        "player_id": "cc77354e",
        "minute": "79",
        "team": "home"
      },
      {
        "type": "card",
        "card_type": "yellow",
        "player_name": "Players",
        "player_id": null,
        "minute": "74",
        "team": "home"
      }
    ],
    "substitutions": [
      {
        "type": "substitution",
        "player_name": "Ben Johnson",
        "player_id": "9319781b",
        "minute": "23",
        "team": "home",
        "substituted_for": "Vladimír Coufal"
      },
      {
        "type": "substitution",
        "player_name": "Emerson Palmieri",
        "player_id": "e0bc6fdc",
        "minute": "46",
        "team": "home",
        "substituted_for": "Saïd Benrahma"
      },
      {
        "type": "substitution",
        "player_name": "Gianluca Scamacca",
        "player_id": "8790f988",
        "minute": "65",
        "team": "home",
        "substituted_for": "Michail Antonio"
      },
      {
        "type": "substitution",
        "player_name": "Douglas Luiz",
        "player_id": "6f7d826d",
        "minute": "66",
        "team": "home",
        "substituted_for": "Jacob Ramsey"
      },
      {
        "type": "substitution",
        "player_name": "Philippe Coutinho",
        "player_id": "0ef89a37",
        "minute": "66",
        "team": "home",
        "substituted_for": "Emi Buendía"
      },
      {
        "type": "substitution",
        "player_name": "Danny Ings",
        "player_id": "07802f7f",
        "minute": "78",
        "team": "home",
        "substituted_for": "Leon Bailey"
      },
      {
        "type": "substitution",
        "player_name": "John McGinn",
        "player_id": "90f91999",
        "minute": "90+1",
        "team": "home",
        "substituted_for": "Cameron Archer"
      }
    ],
    "other": []
  },
  "player_stats": {
    "home": [
      {
        "player_name": "Danny Ings",
        "player_id": "07802f7f",
        "jersey_number": 9,
        "position": "FW",
        "minutes": 77,
        "goals": 0,
        "assists": 0,
        "shots": 1,
        "shots_on_target": 0,
        "passes": 15,
        "pass_accuracy": 66.7,
        "tackles": 0,
        "interceptions": 0,
        "fouls": null,
        "cards": null
      },
      {
        "player_name": "Leon Bailey",
        "player_id": "3a233281",
        "jersey_number": 31,
        "position": "FW,RW",
        "minutes": 13,
        "goals": 0,
        "assists": 0,
        "shots": 1,
        "shots_on_target": 0,
        "passes": 9,
        "pass_accuracy": 55.6,
        "tackles": 0,
        "interceptions": 0,
        "fouls": null,
        "cards": null
      },
      {
        "player_name": "Ollie Watkins",
        "player_id": "aed3a70f",
        "jersey_number": 11,
        "position": "FW",
        "minutes": 90,
        "goals": 0,
        "assists": 0,
        "shots": 2,
        "shots_on_target": 1,
        "passes": 18,
        "pass_accuracy": 88.9,
        "tackles": 0,
        "interceptions": 2,
        "fouls": null,
        "cards": null
      },
      {
        "player_name": "Philippe Coutinho",
        "player_id": "0ef89a37",
        "jersey_number": 23,
        "position": "AM",
        "minutes": 65,
        "goals": 0,
        "assists": 0,
        "shots": 1,
        "shots_on_target": 1,
        "passes": 38,
        "pass_accuracy": 78.9,
        "tackles": 1,
        "interceptions": 0,
        "fouls": null,
        "cards": null
      },
      {
        "player_name": "Emi Buendía",
        "player_id": "66b76d44",
        "jersey_number": 10,
        "position": "AM",
        "minutes": 25,
        "goals": 0,
        "assists": 0,
        "shots": 0,
        "shots_on_target": 0,
        "passes": 27,
        "pass_accuracy": 66.7,
        "tackles": 1,
        "interceptions": 0,
        "fouls": null,
        "cards": null
      },
      {
        "player_name": "John McGinn",
        "player_id": "90f91999",
        "jersey_number": 7,
        "position": "LM",
        "minutes": 89,
        "goals": 0,
        "assists": 0,
        "shots": 2,
        "shots_on_target": 0,
        "passes": 72,
        "pass_accuracy": 86.1,
        "tackles": 3,
        "interceptions": 1,
        "fouls": null,
        "cards": null
      },
      {
        "player_name": "Cameron Archer",
        "player_id": "05e8ca6d",
        "jersey_number": 35,
        "position": "DM",
        "minutes": 1,
        "goals": 0,
        "assists": 0,
        "shots": 0,
        "shots_on_target": 0,
        "passes": 2,
        "pass_accuracy": 100.0,
        "tackles": 0,
        "interceptions": 0,
        "fouls": null,
        "cards": null
      },
      {
        "player_name": "Boubacar Kamara",
        "player_id": "cc77354e",
        "jersey_number": 44,
        "position": "CM,DM",
        "minutes": 90,
        "goals": 0,
        "assists": 0,
        "shots": 0,
        "shots_on_target": 0,
        "passes": 72,
        "pass_accuracy": 93.1,
        "tackles": 3,
        "interceptions": 0,
        "fouls": null,
        "cards": "1 yellow"
      },
      {
        "player_name": "Douglas Luiz",
        "player_id": "6f7d826d",
        "jersey_number": 6,
        "position": "RM",
        "minutes": 65,
        "goals": 0,
        "assists": 0,
        "shots": 0,
        "shots_on_target": 0,
        "passes": 52,
        "pass_accuracy": 82.7,
        "tackles": 0,
        "interceptions": 2,
        "fouls": null,
        "cards": null
      },
      {
        "player_name": "Jacob Ramsey",
        "player_id": "1544f145",
        "jersey_number": 41,
        "position": "RM,LW",
        "minutes": 25,
        "goals": 0,
        "assists": 0,
        "shots": 1,
        "shots_on_target": 1,
        "passes": 17,
        "pass_accuracy": 94.1,
        "tackles": 0,
        "interceptions": 0,
        "fouls": null,
        "cards": null
      },
      {
        "player_name": "Lucas Digne",
        "player_id": "1b84dbe1",
        "jersey_number": 27,
        "position": "LB",
        "minutes": 90,
        "goals": 0,
        "assists": 0,
        "shots": 0,
        "shots_on_target": 0,
        "passes": 87,
        "pass_accuracy": 66.7,
        "tackles": 1,
        "interceptions": 0,
        "fouls": null,
        "cards": null
      },
      {
        "player_name": "Calum Chambers",
        "player_id": "dc6f5bdd",
        "jersey_number": 16,
        "position": "CB",
        "minutes": 90,
        "goals": 0,
        "assists": 0,
        "shots": 0,
        "shots_on_target": 0,
        "passes": 73,
        "pass_accuracy": 86.3,
        "tackles": 2,
        "interceptions": 3,
        "fouls": null,
        "cards": null
      },
      {
        "player_name": "Ezri Konsa",
        "player_id": "0313a347",
        "jersey_number": 4,
        "position": "CB",
        "minutes": 90,
        "goals": 0,
        "assists": 0,
        "shots": 0,
        "shots_on_target": 0,
        "passes": 70,
        "pass_accuracy": 92.9,
        "tackles": 1,
        "interceptions": 2,
        "fouls": null,
        "cards": null
      },
      {
        "player_name": "Matty Cash",
        "player_id": "2389cdc2",
        "jersey_number": 2,
        "position": "RB",
        "minutes": 90,
        "goals": 0,
        "assists": 0,
        "shots": 1,
        "shots_on_target": 0,
        "passes": 49,
        "pass_accuracy": 77.6,
        "tackles": 5,
        "interceptions": 3,
        "fouls": null,
        "cards": "1 yellow"
      },
      {
        "player_name": "Emiliano Martínez",
        "player_id": "7956236f",
        "jersey_number": 1,
        "position": "GK",
        "minutes": 90,
        "goals": 0,
        "assists": 0,
        "shots": 0,
        "shots_on_target": 0,
        "passes": 38,
        "pass_accuracy": 78.9,
        "tackles": 0,
        "interceptions": 0,
        "fouls": null,
        "cards": null
      }
    ],
    "away": [
      {
        "player_name": "Gianluca Scamacca",
        "player_id": "8790f988",
        "jersey_number": 7,
        "position": "FW",
        "minutes": 64,
        "goals": 0,
        "assists": 0,
        "shots": 1,
        "shots_on_target": 1,
        "passes": 13,
        "pass_accuracy": 69.2,
        "tackles": 0,
        "interceptions": 0,
        "fouls": null,
        "cards": null
      },
      {
        "player_name": "Michail Antonio",
        "player_id": "ac05f970",
        "jersey_number": 9,
        "position": "FW",
        "minutes": 26,
        "goals": 0,
        "assists": 0,
        "shots": 0,
        "shots_on_target": 0,
        "passes": 9,
        "pass_accuracy": 66.7,
        "tackles": 0,
        "interceptions": 0,
        "fouls": null,
        "cards": null
      },
      {
        "player_name": "Jarrod Bowen",
        "player_id": "79c84d1c",
        "jersey_number": 20,
        "position": "FW,RW",
        "minutes": 90,
        "goals": 0,
        "assists": 0,
        "shots": 1,
        "shots_on_target": 0,
        "passes": 20,
        "pass_accuracy": 60.0,
        "tackles": 3,
        "interceptions": 0,
        "fouls": null,
        "cards": null
      },
      {
        "player_name": "Pablo Fornals",
        "player_id": "82927de4",
        "jersey_number": 8,
        "position": "CM,LM",
        "minutes": 90,
        "goals": 1,
        "assists": 0,
        "shots": 2,
        "shots_on_target": 1,
        "passes": 44,
        "pass_accuracy": 63.6,
        "tackles": 3,
        "interceptions": 2,
        "fouls": null,
        "cards": null
      },
      {
        "player_name": "Declan Rice",
        "player_id": "1c7012b8",
        "jersey_number": 41,
        "position": "CM",
        "minutes": 90,
        "goals": 0,
        "assists": 1,
        "shots": 1,
        "shots_on_target": 0,
        "passes": 55,
        "pass_accuracy": 85.5,
        "tackles": 1,
        "interceptions": 1,
        "fouls": null,
        "cards": null
      },
      {
        "player_name": "Tomáš Souček",
        "player_id": "6613c819",
        "jersey_number": 28,
        "position": "CM,RM",
        "minutes": 90,
        "goals": 0,
        "assists": 0,
        "shots": 0,
        "shots_on_target": 0,
        "passes": 38,
        "pass_accuracy": 86.8,
        "tackles": 2,
        "interceptions": 4,
        "fouls": null,
        "cards": null
      },
      {
        "player_name": "Emerson Palmieri",
        "player_id": "e0bc6fdc",
        "jersey_number": 33,
        "position": "WB",
        "minutes": 45,
        "goals": 0,
        "assists": 0,
        "shots": 0,
        "shots_on_target": 0,
        "passes": 23,
        "pass_accuracy": 78.3,
        "tackles": 0,
        "interceptions": 1,
        "fouls": null,
        "cards": null
      },
      {
        "player_name": "Saïd Benrahma",
        "player_id": "5a04fd92",
        "jersey_number": 22,
        "position": "LW,WB",
        "minutes": 45,
        "goals": 0,
        "assists": 0,
        "shots": 1,
        "shots_on_target": 0,
        "passes": 22,
        "pass_accuracy": 77.3,
        "tackles": 1,
        "interceptions": 0,
        "fouls": null,
        "cards": null
      },
      {
        "player_name": "Ben Johnson",
        "player_id": "9319781b",
        "jersey_number": 2,
        "position": "WB",
        "minutes": 22,
        "goals": 0,
        "assists": 0,
        "shots": 0,
        "shots_on_target": 0,
        "passes": 11,
        "pass_accuracy": 72.7,
        "tackles": 1,
        "interceptions": 2,
        "fouls": null,
        "cards": null
      },
      {
        "player_name": "Vladimír Coufal",
        "player_id": "fdf3cb77",
        "jersey_number": 5,
        "position": "WB,RB",
        "minutes": 68,
        "goals": 0,
        "assists": 0,
        "shots": 0,
        "shots_on_target": 0,
        "passes": 47,
        "pass_accuracy": 53.2,
        "tackles": 0,
        "interceptions": 3,
        "fouls": null,
        "cards": null
      },
      {
        "player_name": "Aaron Cresswell",
        "player_id": "4f974391",
        "jersey_number": 3,
        "position": "CB,LB",
        "minutes": 90,
        "goals": 0,
        "assists": 0,
        "shots": 1,
        "shots_on_target": 0,
        "passes": 67,
        "pass_accuracy": 82.1,
        "tackles": 1,
        "interceptions": 1,
        "fouls": null,
        "cards": null
      },
      {
        "player_name": "Kurt Zouma",
        "player_id": "ce4246f5",
        "jersey_number": 4,
        "position": "CB",
        "minutes": 90,
        "goals": 0,
        "assists": 0,
        "shots": 0,
        "shots_on_target": 0,
        "passes": 46,
        "pass_accuracy": 84.8,
        "tackles": 0,
        "interceptions": 0,
        "fouls": null,
        "cards": null
      },
      {
        "player_name": "Thilo Kehrer",
        "player_id": "51dbeea9",
        "jersey_number": 24,
        "position": "CB",
        "minutes": 90,
        "goals": 0,
        "assists": 0,
        "shots": 0,
        "shots_on_target": 0,
        "passes": 47,
        "pass_accuracy": 85.1,
        "tackles": 1,
        "interceptions": 2,
        "fouls": null,
        "cards": null
      },
      {
        "player_name": "Łukasz Fabiański",
        "player_id": "9328b835",
        "jersey_number": 1,
        "position": "GK",
        "minutes": 90,
        "goals": 0,
        "assists": 0,
        "shots": 0,
        "shots_on_target": 0,
        "passes": 28,
        "pass_accuracy": 82.1,
        "tackles": 0,
        "interceptions": 0,
        "fouls": null,
        "cards": null
      }
    ]
  },
  "team_stats": {
    "home": {
      "possession": 58.0,
      "passes_completed": 523,
      "passes_attempted": 639,
      "passing_accuracy": 82.0,
      "shots": 9,
      "shots_on_target": 3,
      "saves": 1,
      "fouls": 10,
      "corners": 3,
      "crosses": 26,
      "touches": 741,
      "tackles": 17,
      "interceptions": 13,
      "aerials_won": 13,
      "clearances": 17,
      "offsides": 2,
      "goal_kicks": 5,
      "throw_ins": 25,
      "long_balls": 68,
      "yellow_cards": 2,
      "red_cards": 0
    },
    "away": {
      "possession": 42.0,
      "passes_completed": 360,
      "passes_attempted": 470,
      "passing_accuracy": 77.0,
      "shots": 7,
      "shots_on_target": 2,
      "saves": 3,
      "fouls": 10,
      "corners": 2,
      "crosses": 19,
      "touches": 573,
      "tackles": 13,
      "interceptions": 16,
      "aerials_won": 9,
      "clearances": 30,
      "offsides": 1,
      "goal_kicks": 9,
      "throw_ins": 23,
      "long_balls": 63,
      "yellow_cards": 0,
      "red_cards": 0
    }
  },
  "date": "August 28, 2022"
}