{
  "match_info": {
    "date": "2025-12-07",
    "home_score": 1,
    "away_score": 2,
    "attendance": 27283,
    "referee": "Samuel Barrott",
    "venue": "Craven Cottage, London"
  },
  "home_team": {
    "name": "Fulham",
    "fbref_id": "fd962109",
    "manager": "Marco Silva",
    "captain": "Joachim Andersen"
  },
  "away_team": {
    "name": "Crystal Palace",
    "fbref_id": "47c64c55",
    "manager": "Oliver Glasner",
    "captain": "Marc Guéhi"
  },
  "lineups": {
    "home": {
      "starting_xi": [
        {
          "name": "Raúl Jiménez",
          "fbref_id": "b561db50",
          "position": "FW",
          "jersey_number": 7
        },
        {
          "name": "Timothy Castagne",
          "fbref_id": "197640fd",
          "position": "LB",
          "jersey_number": 21
        },
        {
          "name": "Calvin Bassey",
          "fbref_id": "a36524bf",
          "position": "CB",
          "jersey_number": 3
        },
        {
          "name": "Joachim Andersen",
          "fbref_id": "e34fc66d",
          "position": "CB",
          "jersey_number": 5
        },
        {
          "name": "Kenny Tete",
          "fbref_id": "77d7c96f",
          "position": "RB",
          "jersey_number": 2
        },
        {
          "name": "Bernd Leno",
          "fbref_id": "2628fd2b",
          "position": "GK",
          "jersey_number": 1
        },
        {
          "name": "Alex Iwobi",
          "fbref_id": "6ca5ec4b",
          "position": "DM",
          "jersey_number": 17
        },
        {
          "name": "Harry Wilson",
          "fbref_id": "c6dc9ecd",
          "position": "RW,AM",
          "jersey_number": 8
        },
        {
          "name": "Samuel Chukwueze",
          "fbref_id": "b8a642fc",
          "position": "LW,RW",
          "jersey_number": 19
        },
        {
          "name": "Sander Berge",
          "fbref_id": "d0b6129f",
          "position": "DM",
          "jersey_number": 16
        },
        {
          "name": "Emile Smith Rowe",
          "fbref_id": "17695062",
          "position": "AM",
          "jersey_number": 32
        }
      ],
      "substitutes": [
        {
          "name": "Benjamin Lecomte",
          "fbref_id": "2fa2a875",
          "position": null,
          "jersey_number": null
        },
        {
          "name": "Tom Cairney",
          "fbref_id": "a8748947",
          "position": "DM",
          "jersey_number": 10
        },
        {
          "name": "Adama Traoré",
          "fbref_id": "9a28eba4",
          "position": "RW",
          "jersey_number": 11
        },
        {
          "name": "Jorge Cuenca",
          "fbref_id": "0abc51f2",
          "position": null,
          "jersey_number": null
        },
        {
          "name": "Jonah Kusi-Asare",
          "fbref_id": "c7c26e61",
          "position": null,
          "jersey_number": null
        },
        {
          "name": "Saša Lukić",
          "fbref_id": "c6e8cf1f",
          "position": "DM",
          "jersey_number": 20
        },
        {
          "name": "Kevin",
          "fbref_id": "93508980",
          "position": "LW",
          "jersey_number": 22
        },
        {
          "name": "Joshua King",
          "fbref_id": "86109b3b",
          "position": "AM",
          "jersey_number": 24
        },
        {
          "name": "Issa Diop",
          "fbref_id": "a712ca2b",
          "position": null,
          "jersey_number": null
        }
      ],
      "formation": null
    },
    "away": {
      "starting_xi": [
        {
          "name": "Daichi Kamada",
          "fbref_id": "15b287da",
          "position": "CM,AM,RM",
          "jersey_number": 18
        },
        {
          "name": "Adam Wharton",
          "fbref_id": "4b542852",
          "position": "CM",
          "jersey_number": 20
        },
        {
          "name": "Tyrick Mitchell",
          "fbref_id": "5cbd1eb0",
          "position": "WB,LB",
          "jersey_number": 3
        },
        {
          "name": "Marc Guéhi",
          "fbref_id": "d0706b27",
          "position": "CB",
          "jersey_number": 6
        },
        {
          "name": "Maxence Lacroix",
          "fbref_id": "277c49ed",
          "position": "CB",
          "jersey_number": 5
        },
        {
          "name": "Chris Richards",
          "fbref_id": "0a3d6d2b",
          "position": "CB",
          "jersey_number": 26
        },
        {
          "name": "Dean Henderson",
          "fbref_id": "e5a76dfe",
          "position": "GK",
          "jersey_number": 1
        },
        {
          "name": "Yeremi Pino",
          "fbref_id": "540ec57b",
          "position": "AM",
          "jersey_number": 10
        },
        {
          "name": "Nathaniel Clyne",
          "fbref_id": "0442183b",
          "position": "WB",
          "jersey_number": 17
        },
        {
          "name": "Jean-Philippe Mateta",
          "fbref_id": "50e6dc35",
          "position": "FW",
          "jersey_number": 14
        },
        {
          "name": "Eddie Nketiah",
          "fbref_id": "a53649b7",
          "position": "AM",
          "jersey_number": 9
        }
      ],
      "substitutes": [
        {
          "name": "Remi Matthews",
          "fbref_id": "27f4f772",
          "position": null,
          "jersey_number": null
        },
        {
          "name": "Walter Benítez",
          "fbref_id": "8a2248b4",
          "position": null,
          "jersey_number": null
        },
        {
          "name": "Jefferson Lerma",
          "fbref_id": "9b5ce51a",
          "position": "CM",
          "jersey_number": 8
        },
        {
          "name": "Christantus Uche",
          "fbref_id": "87941696",
          "position": "FW",
          "jersey_number": 12
        },
        {
          "name": "Will Hughes",
          "fbref_id": "a0666d3e",
          "position": null,
          "jersey_number": null
        },
        {
          "name": "Romain Esse",
          "fbref_id": "87189f25",
          "position": null,
          "jersey_number": null
        },
        {
          "name": "Jaydee Canvot",
          "fbref_id": "3684108d",
          "position": "WB,RB",
          "jersey_number": 23
        },
        {
          "name": "Borna Sosa",
          "fbref_id": "af0d79a9",
          "position": null,
          "jersey_number": null
        },
        {
          "name": "Justin Devenny",
          "fbref_id": "6c2b66fc",
          "position": "LM",
          "jersey_number": 55
        }
      ],
      "formation": null
    }
  },
  "events": {
    "goals": [
      {
        "type": "goal",
        "player_name": "Eddie Nketiah",
        "player_id": "a53649b7",
        "minute": "20",
        "team": "away",
        "assist_player": "Adam Wharton",
        "assist_player_id": "4b542852"
      },
      {
        "type": "goal",
        "player_name": "Harry Wilson",
        "player_id": "c6dc9ecd",
        "minute": "38",
        "team": "away",
        "assist_player": "Raúl Jiménez",
        "assist_player_id": "b561db50"
      },
      {
        "type": "goal",
        "player_name": "Marc Guéhi",
        "player_id": "d0706b27",
        "minute": "87",
        "team": "away",
        "assist_player": "Yeremi Pino",
        "assist_player_id": "540ec57b"
      }
    ],
    "assists": [
      {
        "type": "assist",
        "player_name": "Adam Wharton",
        "player_id": "4b542852",
        "minute": "20",
        "team": "away"
      },
      {
        "type": "assist",
        "player_name": "Raúl Jiménez",
        "player_id": "b561db50",
        "minute": "38",
        "team": "away"
      },
      {
        "type": "assist",
        "player_name": "Yeremi Pino",
        "player_id": "540ec57b",
        "minute": "87",
        "team": "away"
      }
    ],
    "cards": [
      {
        "type": "card",
        "card_type": "yellow",
        "player_name": "Players",
        "player_id": null,
        "minute": "38",
        "team": "home"
      }
    ],
    "substitutions": [
      {
        "type": "substitution",
        "player_name": "Eddie Nketiah",
        "player_id": "a53649b7",
        "minute": "65",
        "team": "home",
        "substituted_for": "Jefferson Lerma"
      },
      {
        "type": "substitution",
        "player_name": "Jean-Philippe Mateta",
        "player_id": "50e6dc35",
        "minute": "66",
        "team": "home",
        "substituted_for": "Christantus Uche"
      },
      {
        "type": "substitution",
        "player_name": "Emile Smith Rowe",
        "player_id": "17695062",
        "minute": "68",
        "team": "home",
        "substituted_for": "Kevin"
      },
      {
        "type": "substitution",
        "player_name": "Samuel Chukwueze",
        "player_id": "b8a642fc",
        "minute": "76",
        "team": "home",
        "substituted_for": "Joshua King"
      },
      {
        "type": "substitution",
        "player_name": "Sander Berge",
        "player_id": "d0b6129f",
        "minute": "76",
        "team": "home",
        "substituted_for": "Saša Lukić"
      },
      {
        "type": "substitution",
        "player_name": "Nathaniel Clyne",
        "player_id": "0442183b",
        "minute": "77",
        "team": "home",
        "substituted_for": "Jaydee Canvot"
      },
      {
        "type": "substitution",
        "player_name": "Harry Wilson",
        "player_id": "c6dc9ecd",
        "minute": "88",
        "team": "home",
        "substituted_for": "Tom Cairney"
      },
      {
        "type": "substitution",
        "player_name": "Alex Iwobi",
        "player_id": "6ca5ec4b",
        "minute": "89",
        "team": "home",
        "substituted_for": "Adama Traoré"
      },
      {
        "type": "substitution",
        "player_name": "Yeremi Pino",
        "player_id": "540ec57b",
        "minute": "90+2",
        "team": "home",
        "substituted_for": "Justin Devenny"
      }
    ],
    "other": []
  },
  "player_stats": {
    "home": [
      {
        "player_name": "Raúl Jiménez",
        "player_id": "b561db50",
        "jersey_number": 7,
        "position": "FW",
        "minutes": 90,
        "goals": 0,
        "assists": 1,
        "shots": 2,
        "shots_on_target": 0,
        "passes": 16,
        "pass_accuracy": 56.3,
        "tackles": 0,
        "interceptions": 0,
        "fouls": null,
        "cards": null
      },
      {
        "player_name": "Samuel Chukwueze",
        "player_id": "b8a642fc",
        "jersey_number": 19,
        "position": "LW,RW",
        "minutes": 75,
        "goals": 0,
        "assists": 0,
        "shots": 1,
        "shots_on_target": 0,
        "passes": 32,
        "pass_accuracy": 71.9,
        "tackles": 1,
        "interceptions": 0,
        "fouls": null,
        "cards": null
      },
      {
        "player_name": "Joshua King",
        "player_id": "86109b3b",
        "jersey_number": 24,
        "position": "AM",
        "minutes": 15,
        "goals": 0,
        "assists": 0,
        "shots": 0,
        "shots_on_target": 0,
        "passes": 5,
        "pass_accuracy": 100.0,
        "tackles": 0,
        "interceptions": 0,
        "fouls": null,
        "cards": null
      },
      {
        "player_name": "Harry Wilson",
        "player_id": "c6dc9ecd",
        "jersey_number": 8,
        "position": "RW,AM",
        "minutes": 87,
        "goals": 1,
        "assists": 0,
        "shots": 2,
        "shots_on_target": 2,
        "passes": 32,
        "pass_accuracy": 78.1,
        "tackles": 0,
        "interceptions": 0,
        "fouls": null,
        "cards": null
      },
      {
        "player_name": "Tom Cairney",
        "player_id": "a8748947",
        "jersey_number": 10,
        "position": "DM",
        "minutes": 3,
        "goals": 0,
        "assists": 0,
        "shots": 0,
        "shots_on_target": 0,
        "passes": 5,
        "pass_accuracy": 100.0,
        "tackles": 0,
        "interceptions": 0,
        "fouls": null,
        "cards": null
      },
      {
        "player_name": "Emile Smith Rowe",
        "player_id": "17695062",
        "jersey_number": 32,
        "position": "AM",
        "minutes": 67,
        "goals": 0,
        "assists": 0,
        "shots": 2,
        "shots_on_target": 1,
        "passes": 27,
        "pass_accuracy": 85.2,
        "tackles": 0,
        "interceptions": 2,
        "fouls": null,
        "cards": null
      },
      {
        "player_name": "Kevin",
        "player_id": "93508980",
        "jersey_number": 22,
        "position": "LW",
        "minutes": 23,
        "goals": 0,
        "assists": 0,
        "shots": 1,
        "shots_on_target": 0,
        "passes": 15,
        "pass_accuracy": 60.0,
        "tackles": 0,
        "interceptions": 0,
        "fouls": null,
        "cards": null
      },
      {
        "player_name": "Alex Iwobi",
        "player_id": "6ca5ec4b",
        "jersey_number": 17,
        "position": "DM",
        "minutes": 88,
        "goals": 0,
        "assists": 0,
        "shots": 1,
        "shots_on_target": 1,
        "passes": 63,
        "pass_accuracy": 82.5,
        "tackles": 3,
        "interceptions": 0,
        "fouls": null,
        "cards": null
      },
      {
        "player_name": "Adama Traoré",
        "player_id": "9a28eba4",
        "jersey_number": 11,
        "position": "RW",
        "minutes": 2,
        "goals": 0,
        "assists": 0,
        "shots": 0,
        "shots_on_target": 0,
        "passes": 4,
        "pass_accuracy": 100.0,
        "tackles": 0,
        "interceptions": 0,
        "fouls": null,
        "cards": null
      },
      {
        "player_name": "Sander Berge",
        "player_id": "d0b6129f",
        "jersey_number": 16,
        "position": "DM",
        "minutes": 75,
        "goals": 0,
        "assists": 0,
        "shots": 0,
        "shots_on_target": 0,
        "passes": 43,
        "pass_accuracy": 93.0,
        "tackles": 1,
        "interceptions": 0,
        "fouls": null,
        "cards": null
      },
      {
        "player_name": "Saša Lukić",
        "player_id": "c6e8cf1f",
        "jersey_number": 20,
        "position": "DM",
        "minutes": 15,
        "goals": 0,
        "assists": 0,
        "shots": 0,
        "shots_on_target": 0,
        "passes": 9,
        "pass_accuracy": 88.9,
        "tackles": 0,
        "interceptions": 1,
        "fouls": null,
        "cards": null
      },
      {
        "player_name": "Timothy Castagne",
        "player_id": "197640fd",
        "jersey_number": 21,
        "position": "LB",
        "minutes": 90,
        "goals": 0,
        "assists": 0,
        "shots": 0,
        "shots_on_target": 0,
        "passes": 62,
        "pass_accuracy": 82.3,
        "tackles": 1,
        "interceptions": 1,
        "fouls": null,
        "cards": null
      },
      {
        "player_name": "Calvin Bassey",
        "player_id": "a36524bf",
        "jersey_number": 3,
        "position": "CB",
        "minutes": 90,
        "goals": 0,
        "assists": 0,
        "shots": 1,
        "shots_on_target": 0,
        "passes": 121,
        "pass_accuracy": 89.3,
        "tackles": 2,
        "interceptions": 0,
        "fouls": null,
        "cards": null
      },
      {
        "player_name": "Joachim Andersen",
        "player_id": "e34fc66d",
        "jersey_number": 5,
        "position": "CB",
        "minutes": 90,
        "goals": 0,
        "assists": 0,
        "shots": 0,
        "shots_on_target": 0,
        "passes": 153,
        "pass_accuracy": 88.9,
        "tackles": 0,
        "interceptions": 2,
        "fouls": null,
        "cards": null
      },
      {
        "player_name": "Kenny Tete",
        "player_id": "77d7c96f",
        "jersey_number": 2,
        "position": "RB",
        "minutes": 90,
        "goals": 0,
        "assists": 0,
        "shots": 2,
        "shots_on_target": 0,
        "passes": 74,
        "pass_accuracy": 87.8,
        "tackles": 4,
        "interceptions": 2,
        "fouls": null,
        "cards": null
      },
      {
        "player_name": "Bernd Leno",
        "player_id": "2628fd2b",
        "jersey_number": 1,
        "position": "GK",
        "minutes": 90,
        "goals": 0,
        "assists": 0,
        "shots": 0,
        "shots_on_target": 0,
        "passes": 28,
        "pass_accuracy": 92.9,
        "tackles": 0,
        "interceptions": 0,
        "fouls": null,
        "cards": null
      }
    ],
    "away": [
      {
        "player_name": "Jean-Philippe Mateta",
        "player_id": "50e6dc35",
        "jersey_number": 14,
        "position": "FW",
        "minutes": 65,
        "goals": 0,
        "assists": 0,
        "shots": 2,
        "shots_on_target": 1,
        "passes": 11,
        "pass_accuracy": 72.7,
        "tackles": 1,
        "interceptions": 0,
        "fouls": null,
        "cards": null
      },
      {
        "player_name": "Christantus Uche",
        "player_id": "87941696",
        "jersey_number": 12,
        "position": "FW",
        "minutes": 25,
        "goals": 0,
        "assists": 0,
        "shots": 1,
        "shots_on_target": 1,
        "passes": 5,
        "pass_accuracy": 100.0,
        "tackles": 0,
        "interceptions": 0,
        "fouls": null,
        "cards": null
      },
      {
        "player_name": "Yeremi Pino",
        "player_id": "540ec57b",
        "jersey_number": 10,
        "position": "AM",
        "minutes": 89,
        "goals": 0,
        "assists": 1,
        "shots": 2,
        "shots_on_target": 0,
        "passes": 37,
        "pass_accuracy": 75.7,
        "tackles": 1,
        "interceptions": 2,
        "fouls": null,
        "cards": null
      },
      {
        "player_name": "Justin Devenny",
        "player_id": "6c2b66fc",
        "jersey_number": 55,
        "position": "LM",
        "minutes": 1,
        "goals": 0,
        "assists": 0,
        "shots": 0,
        "shots_on_target": 0,
        "passes": 2,
        "pass_accuracy": 100.0,
        "tackles": 0,
        "interceptions": 0,
        "fouls": null,
        "cards": null
      },
      {
        "player_name": "Eddie Nketiah",
        "player_id": "a53649b7",
        "jersey_number": 9,
        "position": "AM",
        "minutes": 64,
        "goals": 1,
        "assists": 0,
        "shots": 2,
        "shots_on_target": 2,
        "passes": 11,
        "pass_accuracy": 72.7,
        "tackles": 1,
        "interceptions": 0,
        "fouls": null,
        "cards": null
      },
      {
        "player_name": "Jefferson Lerma",
        "player_id": "9b5ce51a",
        "jersey_number": 8,
        "position": "CM",
        "minutes": 26,
        "goals": 0,
        "assists": 0,
        "shots": 0,
        "shots_on_target": 0,
        "passes": 16,
        "pass_accuracy": 68.8,
        "tackles": 1,
        "interceptions": 0,
        "fouls": null,
        "cards": null
      },
      {
        "player_name": "Daichi Kamada",
        "player_id": "15b287da",
        "jersey_number": 18,
        "position": "CM,AM,RM",
        "minutes": 90,
        "goals": 0,
        "assists": 0,
        "shots": 1,
        "shots_on_target": 0,
        "passes": 41,
        "pass_accuracy": 90.2,
        "tackles": 1,
        "interceptions": 1,
        "fouls": null,
        "cards": null
      },
      {
        "player_name": "Adam Wharton",
        "player_id": "4b542852",
        "jersey_number": 20,
        "position": "CM",
        "minutes": 90,
        "goals": 0,
        "assists": 1,
        "shots": 1,
        "shots_on_target": 0,
        "passes": 44,
        "pass_accuracy": 93.2,
        "tackles": 2,
        "interceptions": 3,
        "fouls": null,
        "cards": null
      },
      {
        "player_name": "Tyrick Mitchell",
        "player_id": "5cbd1eb0",
        "jersey_number": 3,
        "position": "WB,LB",
        "minutes": 90,
        "goals": 0,
        "assists": 0,
        "shots": 0,
        "shots_on_target": 0,
        "passes": 34,
        "pass_accuracy": 67.6,
        "tackles": 3,
        "interceptions": 0,
        "fouls": null,
        "cards": null
      },
      {
        "player_name": "Nathaniel Clyne",
        "player_id": "0442183b",
        "jersey_number": 17,
        "position": "WB",
        "minutes": 76,
        "goals": 0,
        "assists": 0,
        "shots": 1,
        "shots_on_target": 0,
        "passes": 24,
        "pass_accuracy": 70.8,
        "tackles": 2,
        "interceptions": 1,
        "fouls": null,
        "cards": null
      },
      {
        "player_name": "Jaydee Canvot",
        "player_id": "3684108d",
        "jersey_number": 23,
        "position": "WB,RB",
        "minutes": 14,
        "goals": 0,
        "assists": 0,
        "shots": 0,
        "shots_on_target": 0,
        "passes": 8,
        "pass_accuracy": 75.0,
        "tackles": 0,
        "interceptions": 0,
        "fouls": null,
        "cards": null
      },
      {
        "player_name": "Marc Guéhi",
        "player_id": "d0706b27",
        "jersey_number": 6,
        "position": "CB",
        "minutes": 90,
        "goals": 1,
        "assists": 0,
        "shots": 1,
        "shots_on_target": 1,
        "passes": 49,
        "pass_accuracy": 89.8,
        "tackles": 2,
        "interceptions": 1,
        "fouls": null,
        "cards": null
      },
      {
        "player_name": "Maxence Lacroix",
        "player_id": "277c49ed",
        "jersey_number": 5,
        "position": "CB",
        "minutes": 90,
        "goals": 0,
        "assists": 0,
        "shots": 0,
        "shots_on_target": 0,
        "passes": 43,
        "pass_accuracy": 88.4,
        "tackles": 4,
        "interceptions": 0,
        "fouls": null,
        "cards": null
      },
      {
        "player_name": "Chris Richards",
        "player_id": "0a3d6d2b",
        "jersey_number": 26,
        "position": "CB",
        "minutes": 90,
        "goals": 0,
        "assists": 0,
        "shots": 0,
        "shots_on_target": 0,
        "passes": 44,
        "pass_accuracy": 72.7,
        "tackles": 2,
        "interceptions": 1,
        "fouls": null,
        "cards": null
      },
      {
        "player_name": "Dean Henderson",
        "player_id": "e5a76dfe",
        "jersey_number": 1,
        "position": "GK",
        "minutes": 90,
        "goals": 0,
        "assists": 0,
        "shots": 0,
        "shots_on_target": 0,
        "passes": 34,
        "pass_accuracy": 61.8,
        "tackles": 0,
        "interceptions": 0,
        "fouls": null,
        "cards": null
      }
    ]
  },
  "team_stats": {
    "home": {
      "possession": 63.0,
      "passes_completed": 589,
      "passes_attempted": 689,
      "passing_accuracy": 85.0,
      "shots": 12,
      "shots_on_target": 4,
      "saves": 3,
      "fouls": 5,
      "corners": 6,
      "crosses": 19,
      "touches": 797,
      "tackles": 12,
      "interceptions": 8,
      "aerials_won": 15,
      "clearances": 27,
      "offsides": 3,
      "goal_kicks": 7,
      "throw_ins": 25,
      "long_balls": 65,
      "yellow_cards": 0,
      "red_cards": 0
    },
    "away": {
      "possession": 37.0,
      "passes_completed": 321,
      "passes_attempted": 403,
      "passing_accuracy": 80.0,
      "shots": 11,
      "shots_on_target": 5,
      "saves": 3,
      "fouls": 8,
      "corners": 4,
      "crosses": 13,
      "touches": 536,
      "tackles": 20,
      "interceptions": 9,
      "aerials_won": 7,
      "clearances": 29,
      "offsides": 2,
      "goal_kicks": 9,
      "throw_ins": 14,
      "long_balls": 54,
      "yellow_cards": 0,
      "red_cards": 0
    }
  },
  "date": "December 7, 2025"
}