{
  "match_info": {
    "date": "2024-08-31",
    "home_score": 1,
    "away_score": 1,
    "attendance": 29517,
    "referee": "Lewis Smith",
    "venue": "Portman Road Stadium, Ipswich"
  },
  "home_team": {
    "name": "Ipswich Town",
    "fbref_id": "b74092de",
    "manager": "Kieran McKenna",
    "captain": "Sam Morsy"
  },
  "away_team": {
    "name": "Fulham",
    "fbref_id": "fd962109",
    "manager": "Marco Silva",
    "captain": "Bernd Leno"
  },
  "lineups": {
    "home": {
      "starting_xi": [
        {
          "name": "Omari Hutchinson",
          "fbref_id": "bd9553e6",
          "position": "AM,RW",
          "jersey_number": 20
        },
        {
          "name": "Sam Morsy",
          "fbref_id": "a23c0949",
          "position": "DM",
          "jersey_number": 5
        },
        {
          "name": "Leif Davis",
          "fbref_id": "8574c61f",
          "position": "LB",
          "jersey_number": 3
        },
        {
          "name": "Jacob Greaves",
          "fbref_id": "1f169636",
          "position": "CB",
          "jersey_number": 24
        },
        {
          "name": "Luke Woolfenden",
          "fbref_id": "e28e9bec",
          "position": "CB",
          "jersey_number": 6
        },
        {
          "name": "Axel Tuanzebe",
          "fbref_id": "2baec6ce",
          "position": "RB",
          "jersey_number": 40
        },
        {
          "name": "Arijanet Muric",
          "fbref_id": "99aa1a84",
          "position": "GK",
          "jersey_number": 1
        },
        {
          "name": "Chiedozie Ogbene",
          "fbref_id": "788c0277",
          "position": "RW",
          "jersey_number": 21
        },
        {
          "name": "Liam Delap",
          "fbref_id": "dd897ee7",
          "position": "FW",
          "jersey_number": 19
        },
        {
          "name": "Sammie Szmodics",
          "fbref_id": "39944392",
          "position": "LW",
          "jersey_number": 23
        },
        {
          "name": "Kalvin Phillips",
          "fbref_id": "4f565d77",
          "position": "DM",
          "jersey_number": 8
        }
      ],
      "substitutes": [
        {
          "name": "Christian Walton",
          "fbref_id": "c666574f",
          "position": null,
          "jersey_number": null
        },
        {
          "name": "Conor Chaplin",
          "fbref_id": "4ec55b87",
          "position": "AM,RW",
          "jersey_number": 10
        },
        {
          "name": "Jens Cajuste",
          "fbref_id": "928a4a61",
          "position": "DM",
          "jersey_number": 12
        },
        {
          "name": "Ali Al Hamadi",
          "fbref_id": "8450467d",
          "position": "FW",
          "jersey_number": 16
        },
        {
          "name": "Ben Johnson",
          "fbref_id": "9319781b",
          "position": null,
          "jersey_number": null
        },
        {
          "name": "Conor Townsend",
          "fbref_id": "4dc4f138",
          "position": null,
          "jersey_number": null
        },
        {
          "name": "Massimo Luongo",
          "fbref_id": "967ac6e1",
          "position": null,
          "jersey_number": null
        },
        {
          "name": "Dara O'Shea",
          "fbref_id": "1d042188",
          "position": null,
          "jersey_number": null
        },
        {
          "name": "Jack Clarke",
          "fbref_id": "e16932d8",
          "position": "LW",
          "jersey_number": 47
        }
      ],
      "formation": null
    },
    "away": {
      "starting_xi": [
        {
          "name": "Adama Traoré",
          "fbref_id": "9a28eba4",
          "position": "RW,LW",
          "jersey_number": 11
        },
        {
          "name": "Antonee Robinson",
          "fbref_id": "289601e6",
          "position": "LB",
          "jersey_number": 33
        },
        {
          "name": "Calvin Bassey",
          "fbref_id": "a36524bf",
          "position": "CB",
          "jersey_number": 3
        },
        {
          "name": "Issa Diop",
          "fbref_id": "a712ca2b",
          "position": "CB",
          "jersey_number": 31
        },
        {
          "name": "Kenny Tete",
          "fbref_id": "77d7c96f",
          "position": "RB",
          "jersey_number": 2
        },
        {
          "name": "Bernd Leno",
          "fbref_id": "2628fd2b",
          "position": "GK",
          "jersey_number": 1
        },
        {
          "name": "Alex Iwobi",
          "fbref_id": "6ca5ec4b",
          "position": "LW",
          "jersey_number": 17
        },
        {
          "name": "Saša Lukić",
          "fbref_id": "c6e8cf1f",
          "position": "CM,DM",
          "jersey_number": 20
        },
        {
          "name": "Andreas Pereira",
          "fbref_id": "6639e500",
          "position": "RM,AM",
          "jersey_number": 18
        },
        {
          "name": "Rodrigo Muniz",
          "fbref_id": "a755db8c",
          "position": "FW",
          "jersey_number": 9
        },
        {
          "name": "Emile Smith Rowe",
          "fbref_id": "17695062",
          "position": "LM",
          "jersey_number": 32
        }
      ],
      "substitutes": [
        {
          "name": "Steven Benda",
          "fbref_id": "caaa7fab",
          "position": null,
          "jersey_number": null
        },
        {
          "name": "Joachim Andersen",
          "fbref_id": "e34fc66d",
          "position": null,
          "jersey_number": null
        },
        {
          "name": "Harrison Reed",
          "fbref_id": "803ae100",
          "position": "DM",
          "jersey_number": 6
        },
        {
          "name": "Raúl Jiménez",
          "fbref_id": "b561db50",
          "position": "FW",
          "jersey_number": 7
        },
        {
          "name": "Harry Wilson",
          "fbref_id": "c6dc9ecd",
          "position": "RW,LW",
          "jersey_number": 8
        },
        {
          "name": "Tom Cairney",
          "fbref_id": "a8748947",
          "position": "AM",
          "jersey_number": 10
        },
        {
          "name": "Jorge Cuenca",
          "fbref_id": "0abc51f2",
          "position": null,
          "jersey_number": null
        },
        {
          "name": "Sander Berge",
          "fbref_id": "d0b6129f",
          "position": "DM",
          "jersey_number": 16
        },
        {
          "name": "Timothy Castagne",
          "fbref_id": "197640fd",
          "position": null,
          "jersey_number": null
        }
      ],
      "formation": null
    }
  },
  "events": {
    "goals": [
      {
        "type": "goal",
        "player_name": "Liam Delap",
        "player_id": "dd897ee7",
        "minute": "15",
        "team": "away",
        "assist_player": "Leif Davis",
        "assist_player_id": "8574c61f"
      },
      {
        "type": "goal",
        "player_name": "Adama Traoré",
        "player_id": "9a28eba4",
        "minute": "32",
        "team": "away",
        "assist_player": "Antonee Robinson",
        "assist_player_id": "289601e6"
      }
    ],
    "assists": [
      {
        "type": "assist",
        "player_name": "Leif Davis",
        "player_id": "8574c61f",
        "minute": "15",
        "team": "away"
      },
      {
        "type": "assist",
        "player_name": "Antonee Robinson",
        "player_id": "289601e6",
        "minute": "32",
        "team": "away"
      }
    ],
    "cards": [
      {
        "type": "card",
        "card_type": "yellow",
        "player_name": "Sam Morsy",
        "player_id": "a23c0949",
        "minute": "37",
        "team": "home"
      },
      {
        "type": "card",
        "card_type": "yellow",
        "player_name": "Saša Lukić",
        "player_id": "c6e8cf1f",
        "minute": "51",
        "team": "home"
      },
      {
        "type": "card",
        "card_type": "yellow",
        "player_name": "Antonee Robinson",
        "player_id": "289601e6",
        "minute": "58",
        "team": "home"
      },
      {
        "type": "card",
        "card_type": "yellow",
        "player_name": "Adama Traoré",
        "player_id": "9a28eba4",
        "minute": "78",
        "team": "home"
      },
      {
        "type": "card",
        "card_type": "yellow",
        "player_name": "Ali Al Hamadi",
        "player_id": "8450467d",
        "minute": "90+4",
        "team": "home"
      },
      {
        "type": "card",
        "card_type": "yellow",
        "player_name": "Players",
        "player_id": null,
        "minute": "15",
        "team": "home"
      }
    ],
    "substitutions": [
      {
        "type": "substitution",
        "player_name": "Kalvin Phillips",
        "player_id": "4f565d77",
        "minute": "71",
        "team": "home",
        "substituted_for": "Jens Cajuste"
      },
      {
        "type": "substitution",
        "player_name": "Emile Smith Rowe",
        "player_id": "17695062",
        "minute": "72",
        "team": "home",
        "substituted_for": "Sander Berge"
      },
      {
        "type": "substitution",
        "player_name": "Rodrigo Muniz",
        "player_id": "a755db8c",
        "minute": "79",
        "team": "home",
        "substituted_for": "Raúl Jiménez"
      },
      {
        "type": "substitution",
        "player_name": "Sammie Szmodics",
        "player_id": "39944392",
        "minute": "81",
        "team": "home",
        "substituted_for": "Jack Clarke"
      },
      {
        "type": "substitution",
        "player_name": "Liam Delap",
        "player_id": "dd897ee7",
        "minute": "81",
        "team": "home",
        "substituted_for": "Ali Al Hamadi"
      },
      {
        "type": "substitution",
        "player_name": "Saša Lukić",
        "player_id": "c6e8cf1f",
        "minute": "87",
        "team": "home",
        "substituted_for": "Harrison Reed"
      },
      {
        "type": "substitution",
        "player_name": "Alex Iwobi",
        "player_id": "6ca5ec4b",
        "minute": "87",
        "team": "home",
        "substituted_for": "Harry Wilson"
      },
      {
        "type": "substitution",
        "player_name": "Andreas Pereira",
        "player_id": "6639e500",
        "minute": "87",
        "team": "home",
        "substituted_for": "Tom Cairney"
      },
      {
        "type": "substitution",
        "player_name": "Chiedozie Ogbene",
        "player_id": "788c0277",
        "minute": "88",
        "team": "home",
        "substituted_for": "Conor Chaplin"
      }
    ],
    "other": []
  },
  "player_stats": {
    "home": [
      {
        "player_name": "Liam Delap",
        "player_id": "dd897ee7",
        "jersey_number": 19,
        "position": "FW",
        "minutes": 80,
        "goals": 1,
        "assists": 0,
        "shots": 4,
        "shots_on_target": 2,
        "passes": 5,
        "pass_accuracy": 60.0,
        "tackles": 1,
        "interceptions": 0,
        "fouls": null,
        "cards": null
      },
      {
        "player_name": "Ali Al Hamadi",
        "player_id": "8450467d",
        "jersey_number": 16,
        "position": "FW",
        "minutes": 10,
        "goals": 0,
        "assists": 0,
        "shots": 0,
        "shots_on_target": 0,
        "passes": 3,
        "pass_accuracy": 66.7,
        "tackles": 1,
        "interceptions": 0,
        "fouls": null,
        "cards": "1 yellow"
      },
      {
        "player_name": "Sammie Szmodics",
        "player_id": "39944392",
        "jersey_number": 23,
        "position": "LW",
        "minutes": 80,
        "goals": 0,
        "assists": 0,
        "shots": 0,
        "shots_on_target": 0,
        "passes": 16,
        "pass_accuracy": 62.5,
        "tackles": 0,
        "interceptions": 1,
        "fouls": null,
        "cards": null
      },
      {
        "player_name": "Jack Clarke",
        "player_id": "e16932d8",
        "jersey_number": 47,
        "position": "LW",
        "minutes": 10,
        "goals": 0,
        "assists": 0,
        "shots": 2,
        "shots_on_target": 0,
        "passes": 4,
        "pass_accuracy": 25.0,
        "tackles": 0,
        "interceptions": 0,
        "fouls": null,
        "cards": null
      },
      {
        "player_name": "Chiedozie Ogbene",
        "player_id": "788c0277",
        "jersey_number": 21,
        "position": "RW",
        "minutes": 87,
        "goals": 0,
        "assists": 0,
        "shots": 0,
        "shots_on_target": 0,
        "passes": 16,
        "pass_accuracy": 75.0,
        "tackles": 4,
        "interceptions": 0,
        "fouls": null,
        "cards": null
      },
      {
        "player_name": "Conor Chaplin",
        "player_id": "4ec55b87",
        "jersey_number": 10,
        "position": "AM,RW",
        "minutes": 3,
        "goals": 0,
        "assists": 0,
        "shots": 0,
        "shots_on_target": 0,
        "passes": 4,
        "pass_accuracy": 100.0,
        "tackles": 0,
        "interceptions": 0,
        "fouls": null,
        "cards": null
      },
      {
        "player_name": "Omari Hutchinson",
        "player_id": "bd9553e6",
        "jersey_number": 20,
        "position": "AM,RW",
        "minutes": 90,
        "goals": 0,
        "assists": 0,
        "shots": 2,
        "shots_on_target": 1,
        "passes": 32,
        "pass_accuracy": 90.6,
        "tackles": 1,
        "interceptions": 0,
        "fouls": null,
        "cards": null
      },
      {
        "player_name": "Kalvin Phillips",
        "player_id": "4f565d77",
        "jersey_number": 8,
        "position": "DM",
        "minutes": 70,
        "goals": 0,
        "assists": 0,
        "shots": 0,
        "shots_on_target": 0,
        "passes": 35,
        "pass_accuracy": 77.1,
        "tackles": 0,
        "interceptions": 0,
        "fouls": null,
        "cards": null
      },
      {
        "player_name": "Jens Cajuste",
        "player_id": "928a4a61",
        "jersey_number": 12,
        "position": "DM",
        "minutes": 20,
        "goals": 0,
        "assists": 0,
        "shots": 0,
        "shots_on_target": 0,
        "passes": 9,
        "pass_accuracy": 88.9,
        "tackles": 0,
        "interceptions": 0,
        "fouls": null,
        "cards": null
      },
      {
        "player_name": "Sam Morsy",
        "player_id": "a23c0949",
        "jersey_number": 5,
        "position": "DM",
        "minutes": 90,
        "goals": 0,
        "assists": 0,
        "shots": 0,
        "shots_on_target": 0,
        "passes": 60,
        "pass_accuracy": 88.3,
        "tackles": 1,
        "interceptions": 0,
        "fouls": null,
        "cards": "1 yellow"
      },
      {
        "player_name": "Leif Davis",
        "player_id": "8574c61f",
        "jersey_number": 3,
        "position": "LB",
        "minutes": 90,
        "goals": 0,
        "assists": 1,
        "shots": 1,
        "shots_on_target": 0,
        "passes": 48,
        "pass_accuracy": 83.3,
        "tackles": 2,
        "interceptions": 0,
        "fouls": null,
        "cards": null
      },
      {
        "player_name": "Jacob Greaves",
        "player_id": "1f169636",
        "jersey_number": 24,
        "position": "CB",
        "minutes": 90,
        "goals": 0,
        "assists": 0,
        "shots": 1,
        "shots_on_target": 1,
        "passes": 49,
        "pass_accuracy": 83.7,
        "tackles": 0,
        "interceptions": 2,
        "fouls": null,
        "cards": null
      },
      {
        "player_name": "Luke Woolfenden",
        "player_id": "e28e9bec",
        "jersey_number": 6,
        "position": "CB",
        "minutes": 90,
        "goals": 0,
        "assists": 0,
        "shots": 1,
        "shots_on_target": 0,
        "passes": 60,
        "pass_accuracy": 88.3,
        "tackles": 0,
        "interceptions": 0,
        "fouls": null,
        "cards": null
      },
      {
        "player_name": "Axel Tuanzebe",
        "player_id": "2baec6ce",
        "jersey_number": 40,
        "position": "RB",
        "minutes": 90,
        "goals": 0,
        "assists": 0,
        "shots": 0,
        "shots_on_target": 0,
        "passes": 52,
        "pass_accuracy": 86.5,
        "tackles": 3,
        "interceptions": 1,
        "fouls": null,
        "cards": null
      },
      {
        "player_name": "Arijanet Muric",
        "player_id": "99aa1a84",
        "jersey_number": 1,
        "position": "GK",
        "minutes": 90,
        "goals": 0,
        "assists": 0,
        "shots": 0,
        "shots_on_target": 0,
        "passes": 41,
        "pass_accuracy": 78.0,
        "tackles": 0,
        "interceptions": 0,
        "fouls": null,
        "cards": null
      }
    ],
    "away": [
      {
        "player_name": "Rodrigo Muniz",
        "player_id": "a755db8c",
        "jersey_number": 9,
        "position": "FW",
        "minutes": 78,
        "goals": 0,
        "assists": 0,
        "shots": 2,
        "shots_on_target": 1,
        "passes": 8,
        "pass_accuracy": 75.0,
        "tackles": 0,
        "interceptions": 0,
        "fouls": null,
        "cards": null
      },
      {
        "player_name": "Raúl Jiménez",
        "player_id": "b561db50",
        "jersey_number": 7,
        "position": "FW",
        "minutes": 12,
        "goals": 0,
        "assists": 0,
        "shots": 1,
        "shots_on_target": 1,
        "passes": 1,
        "pass_accuracy": 100.0,
        "tackles": 0,
        "interceptions": 0,
        "fouls": null,
        "cards": null
      },
      {
        "player_name": "Alex Iwobi",
        "player_id": "6ca5ec4b",
        "jersey_number": 17,
        "position": "LW",
        "minutes": 86,
        "goals": 0,
        "assists": 0,
        "shots": 1,
        "shots_on_target": 1,
        "passes": 34,
        "pass_accuracy": 88.2,
        "tackles": 0,
        "interceptions": 1,
        "fouls": null,
        "cards": null
      },
      {
        "player_name": "Harry Wilson",
        "player_id": "c6dc9ecd",
        "jersey_number": 8,
        "position": "RW,LW",
        "minutes": 4,
        "goals": 0,
        "assists": 0,
        "shots": 0,
        "shots_on_target": 0,
        "passes": 1,
        "pass_accuracy": 100.0,
        "tackles": 0,
        "interceptions": 0,
        "fouls": null,
        "cards": null
      },
      {
        "player_name": "Adama Traoré",
        "player_id": "9a28eba4",
        "jersey_number": 11,
        "position": "RW,LW",
        "minutes": 90,
        "goals": 1,
        "assists": 0,
        "shots": 1,
        "shots_on_target": 1,
        "passes": 27,
        "pass_accuracy": 77.8,
        "tackles": 0,
        "interceptions": 0,
        "fouls": null,
        "cards": "1 yellow"
      },
      {
        "player_name": "Emile Smith Rowe",
        "player_id": "17695062",
        "jersey_number": 32,
        "position": "LM",
        "minutes": 71,
        "goals": 0,
        "assists": 0,
        "shots": 2,
        "shots_on_target": 0,
        "passes": 37,
        "pass_accuracy": 94.6,
        "tackles": 1,
        "interceptions": 1,
        "fouls": null,
        "cards": null
      },
      {
        "player_name": "Sander Berge",
        "player_id": "d0b6129f",
        "jersey_number": 16,
        "position": "DM",
        "minutes": 19,
        "goals": 0,
        "assists": 0,
        "shots": 0,
        "shots_on_target": 0,
        "passes": 10,
        "pass_accuracy": 100.0,
        "tackles": 2,
        "interceptions": 0,
        "fouls": null,
        "cards": null
      },
      {
        "player_name": "Saša Lukić",
        "player_id": "c6e8cf1f",
        "jersey_number": 20,
        "position": "CM,DM",
        "minutes": 86,
        "goals": 0,
        "assists": 0,
        "shots": 0,
        "shots_on_target": 0,
        "passes": 38,
        "pass_accuracy": 94.7,
        "tackles": 1,
        "interceptions": 3,
        "fouls": null,
        "cards": "1 yellow"
      },
      {
        "player_name": "Harrison Reed",
        "player_id": "803ae100",
        "jersey_number": 6,
        "position": "DM",
        "minutes": 4,
        "goals": 0,
        "assists": 0,
        "shots": 0,
        "shots_on_target": 0,
        "passes": 0,
        "pass_accuracy": null,
        "tackles": 0,
        "interceptions": 0,
        "fouls": null,
        "cards": null
      },
      {
        "player_name": "Andreas Pereira",
        "player_id": "6639e500",
        "jersey_number": 18,
        "position": "RM,AM",
        "minutes": 86,
        "goals": 0,
        "assists": 0,
        "shots": 0,
        "shots_on_target": 0,
        "passes": 54,
        "pass_accuracy": 55.6,
        "tackles": 0,
        "interceptions": 1,
        "fouls": null,
        "cards": null
      },
      {
        "player_name": "Tom Cairney",
        "player_id": "a8748947",
        "jersey_number": 10,
        "position": "AM",
        "minutes": 4,
        "goals": 0,
        "assists": 0,
        "shots": 0,
        "shots_on_target": 0,
        "passes": 4,
        "pass_accuracy": 75.0,
        "tackles": 0,
        "interceptions": 0,
        "fouls": null,
        "cards": null
      },
      {
        "player_name": "Antonee Robinson",
        "player_id": "289601e6",
        "jersey_number": 33,
        "position": "LB",
        "minutes": 90,
        "goals": 0,
        "assists": 1,
        "shots": 0,
        "shots_on_target": 0,
        "passes": 41,
        "pass_accuracy": 78.0,
        "tackles": 1,
        "interceptions": 0,
        "fouls": null,
        "cards": "1 yellow"
      },
      {
        "player_name": "Calvin Bassey",
        "player_id": "a36524bf",
        "jersey_number": 3,
        "position": "CB",
        "minutes": 90,
        "goals": 0,
        "assists": 0,
        "shots": 0,
        "shots_on_target": 0,
        "passes": 71,
        "pass_accuracy": 83.1,
        "tackles": 1,
        "interceptions": 0,
        "fouls": null,
        "cards": null
      },
      {
        "player_name": "Issa Diop",
        "player_id": "a712ca2b",
        "jersey_number": 31,
        "position": "CB",
        "minutes": 90,
        "goals": 0,
        "assists": 0,
        "shots": 1,
        "shots_on_target": 0,
        "passes": 47,
        "pass_accuracy": 89.4,
        "tackles": 2,
        "interceptions": 0,
        "fouls": null,
        "cards": null
      },
      {
        "player_name": "Kenny Tete",
        "player_id": "77d7c96f",
        "jersey_number": 2,
        "position": "RB",
        "minutes": 90,
        "goals": 0,
        "assists": 0,
        "shots": 1,
        "shots_on_target": 0,
        "passes": 51,
        "pass_accuracy": 78.4,
        "tackles": 3,
        "interceptions": 0,
        "fouls": null,
        "cards": null
      },
      {
        "player_name": "Bernd Leno",
        "player_id": "2628fd2b",
        "jersey_number": 1,
        "position": "GK",
        "minutes": 90,
        "goals": 0,
        "assists": 0,
        "shots": 0,
        "shots_on_target": 0,
        "passes": 45,
        "pass_accuracy": 82.2,
        "tackles": 0,
        "interceptions": 0,
        "fouls": null,
        "cards": null
      }
    ]
  },
  "team_stats": {
    "home": {
      "possession": 48.0,
      "passes_completed": 360,
      "passes_attempted": 434,
      "passing_accuracy": 83.0,
      "shots": 11,
      "shots_on_target": 4,
      "saves": 3,
      "fouls": 15,
      "corners": 8,
      "crosses": 16,
      "touches": 529,
      "tackles": 13,
      "interceptions": 4,
      "aerials_won": 11,
      "clearances": 30,
      "offsides": 4,
      "goal_kicks": 4,
      "throw_ins": 7,
      "long_balls": 51,
      "yellow_cards": 2,
      "red_cards": 0
    },
    "away": {
      "possession": 52.0,
      "passes_completed": 383,
      "passes_attempted": 469,
      "passing_accuracy": 82.0,
      "shots": 9,
      "shots_on_target": 4,
      "saves": 3,
      "fouls": 15,
      "corners": 6,
      "crosses": 26,
      "touches": 545,
      "tackles": 11,
      "interceptions": 6,
      "aerials_won": 12,
      "clearances": 13,
      "offsides": 0,
      "goal_kicks": 7,
      "throw_ins": 23,
      "long_balls": 67,
      "yellow_cards": 3,
      "red_cards": 0
    }
  },
  "date": "August 31, 2024"
}