{
  "match_info": {
    "date": "2024-10-05",
    "home_score": 5,
    "away_score": 3,
    "attendance": 16960,
    "referee": "Andy Madley",
    "venue": "Gtech Community Stadium, Brentford"
  },
  "home_team": {
    "name": "Brentford",
    "fbref_id": "cd051869",
    "manager": "Thomas Frank",
    "captain": "Mario Lemina"
  },
  "away_team": {
    "name": "Wolverhampton Wanderers",
    "fbref_id": "8cec06e1",
    "manager": "Gary O'Neil",
    "captain": "Mario Lemina"
  },
  "lineups": {
    "home": {
      "starting_xi": [
        {
          "name": "Keane Lewis-Potter",
          "fbref_id": "41f08ac8",
          "position": "LW,RW",
          "jersey_number": 23
        },
        {
          "name": "Bryan Mbeumo",
          "fbref_id": "6afaebf2",
          "position": "RW,FW",
          "jersey_number": 19
        },
        {
          "name": "Vitaly Janelt",
          "fbref_id": "8449d35e",
          "position": "DM,CM",
          "jersey_number": 27
        },
        {
          "name": "Ethan Pinnock",
          "fbref_id": "e541326e",
          "position": "CB",
          "jersey_number": 5
        },
        {
          "name": "Nathan Collins",
          "fbref_id": "a8c19eb8",
          "position": "CB",
          "jersey_number": 22
        },
        {
          "name": "Sepp van den Berg",
          "fbref_id": "7bf9400b",
          "position": "RB",
          "jersey_number": 4
        },
        {
          "name": "Mark Flekken",
          "fbref_id": "a92ab7be",
          "position": "GK",
          "jersey_number": 1
        },
        {
          "name": "Mikkel Damsgaard",
          "fbref_id": "215f3907",
          "position": "AM,RM",
          "jersey_number": 24
        },
        {
          "name": "Kristoffer Ajer",
          "fbref_id": "a8c0acb7",
          "position": "LB",
          "jersey_number": 20
        },
        {
          "name": "Kevin Schade",
          "fbref_id": "52afb588",
          "position": "FW",
          "jersey_number": 7
        },
        {
          "name": "Christian Nørgaard",
          "fbref_id": "df0a4c90",
          "position": "DM",
          "jersey_number": 6
        }
      ],
      "substitutes": [
        {
          "name": "Hákon Valdimarsson",
          "fbref_id": "57a34cf4",
          "position": null,
          "jersey_number": null
        },
        {
          "name": "Fabio Carvalho",
          "fbref_id": "966e28d0",
          "position": "LW",
          "jersey_number": 14
        },
        {
          "name": "Ben Mee",
          "fbref_id": "8df7a2fb",
          "position": null,
          "jersey_number": null
        },
        {
          "name": "Yehor Yarmoliuk",
          "fbref_id": "907a5d7c",
          "position": "LM",
          "jersey_number": 18
        },
        {
          "name": "Jayden Meghoma",
          "fbref_id": "07382f6c",
          "position": null,
          "jersey_number": null
        },
        {
          "name": "Yunus Emre Konak",
          "fbref_id": "e02b5b36",
          "position": "RM",
          "jersey_number": 26
        },
        {
          "name": "Ryan Trevitt",
          "fbref_id": "732327ae",
          "position": null,
          "jersey_number": null
        },
        {
          "name": "Mads Roerslev",
          "fbref_id": "57c94db2",
          "position": "LB",
          "jersey_number": 30
        },
        {
          "name": "Kim Jisoo",
          "fbref_id": "f4065d9e",
          "position": null,
          "jersey_number": null
        }
      ],
      "formation": null
    },
    "away": {
      "starting_xi": [
        {
          "name": "Jørgen Strand Larsen",
          "fbref_id": "f553b2b3",
          "position": "FW",
          "jersey_number": 9
        },
        {
          "name": "Matheus Cunha",
          "fbref_id": "dc62b55d",
          "position": "LM",
          "jersey_number": 10
        },
        {
          "name": "Mario Lemina",
          "fbref_id": "2b471f99",
          "position": "CM",
          "jersey_number": 5
        },
        {
          "name": "Rayan Aït-Nouri",
          "fbref_id": "9b398aea",
          "position": "LB",
          "jersey_number": 3
        },
        {
          "name": "Toti Gomes",
          "fbref_id": "f0caab96",
          "position": "CB",
          "jersey_number": 24
        },
        {
          "name": "Craig Dawson",
          "fbref_id": "3e9e06cb",
          "position": "CB",
          "jersey_number": 15
        },
        {
          "name": "Nélson Semedo",
          "fbref_id": "d04b94db",
          "position": "RB",
          "jersey_number": 22
        },
        {
          "name": "Sam Johnstone",
          "fbref_id": "9e5708be",
          "position": "GK",
          "jersey_number": 31
        },
        {
          "name": "João Gomes",
          "fbref_id": "8b57ad2c",
          "position": "CM",
          "jersey_number": 8
        },
        {
          "name": "Carlos Forbs",
          "fbref_id": "8a310070",
          "position": "RM",
          "jersey_number": 26
        },
        {
          "name": "André",
          "fbref_id": "ec604e2c",
          "position": "DM",
          "jersey_number": 7
        }
      ],
      "substitutes": [
        {
          "name": "José Sá",
          "fbref_id": "903b6e8b",
          "position": null,
          "jersey_number": 4
        },
        {
          "name": "Jean-Ricner Bellegarde",
          "fbref_id": "10f0fdd3",
          "position": "CM",
          "jersey_number": 27
        },
        {
          "name": "Gonçalo Guedes",
          "fbref_id": "e6bc67d7",
          "position": "RM",
          "jersey_number": 29
        },
        {
          "name": "Hwang Hee-chan",
          "fbref_id": "169fd162",
          "position": "DM",
          "jersey_number": 11
        }
      ],
      "formation": null
    }
  },
  "events": {
    "goals": [
      {
        "type": "goal",
        "player_name": "Nathan Collins",
        "player_id": "a8c19eb8",
        "minute": "2",
        "team": "away",
        "assist_player": "Mikkel Damsgaard",
        "assist_player_id": "215f3907"
      },
      {
        "type": "goal",
        "player_name": "Matheus Cunha",
        "player_id": "dc62b55d",
        "minute": "4",
        "team": "away",
        "assist_player": "Nélson Semedo",
        "assist_player_id": "d04b94db"
      },
      {
        "type": "goal",
        "player_name": "Bryan Mbeumo",
        "player_id": "6afaebf2",
        "minute": "20",
        "team": "away",
        "assist_player": "Nathan Collins",
        "assist_player_id": "a8c19eb8"
      },
      {
        "type": "goal",
        "player_name": "Jørgen Strand Larsen",
        "player_id": "f553b2b3",
        "minute": "26",
        "team": "away",
        "assist_player": "Rayan Aït-Nouri",
        "assist_player_id": "9b398aea"
      },
      {
        "type": "goal",
        "player_name": "Christian Nørgaard",
        "player_id": "df0a4c90",
        "minute": "28",
        "team": "away",
        "assist_player": "Vitaly Janelt",
        "assist_player_id": "8449d35e"
      },
      {
        "type": "goal",
        "player_name": "Ethan Pinnock",
        "player_id": "e541326e",
        "minute": "45+2",
        "team": "away",
        "assist_player": "Mikkel Damsgaard",
        "assist_player_id": "215f3907"
      },
      {
        "type": "goal",
        "player_name": "Fabio Carvalho",
        "player_id": "966e28d0",
        "minute": "90",
        "team": "away",
        "assist_player": "Mikkel Damsgaard",
        "assist_player_id": "215f3907"
      },
      {
        "type": "goal",
        "player_name": "Rayan Aït-Nouri",
        "player_id": "9b398aea",
        "minute": "90+3",
        "team": "away",
        "assist_player": "Jean-Ricner Bellegarde",
        "assist_player_id": "10f0fdd3"
      }
    ],
    "assists": [
      {
        "type": "assist",
        "player_name": "Mikkel Damsgaard",
        "player_id": "215f3907",
        "minute": "2",
        "team": "away"
      },
      {
        "type": "assist",
        "player_name": "Nélson Semedo",
        "player_id": "d04b94db",
        "minute": "4",
        "team": "away"
      },
      {
        "type": "assist",
        "player_name": "Nathan Collins",
        "player_id": "a8c19eb8",
        "minute": "20",
        "team": "away"
      },
      {
        "type": "assist",
        "player_name": "Rayan Aït-Nouri",
        "player_id": "9b398aea",
        "minute": "26",
        "team": "away"
      },
      {
        "type": "assist",
        "player_name": "Vitaly Janelt",
        "player_id": "8449d35e",
        "minute": "28",
        "team": "away"
      },
      {
        "type": "assist",
        "player_name": "Mikkel Damsgaard",
        "player_id": "215f3907",
        "minute": "45+2",
        "team": "away"
      },
      {
        "type": "assist",
        "player_name": "Mikkel Damsgaard",
        "player_id": "215f3907",
        "minute": "90",
        "team": "away"
      },
      {
        "type": "assist",
        "player_name": "Jean-Ricner Bellegarde",
        "player_id": "10f0fdd3",
        "minute": "90+3",
        "team": "away"
      }
    ],
    "cards": [
      {
        "type": "card",
        "card_type": "yellow",
        "player_name": "Craig Dawson",
        "player_id": "3e9e06cb",
        "minute": "42",
        "team": "home"
      },
      {
        "type": "card",
        "card_type": "yellow",
        "player_name": "Kristoffer Ajer",
        "player_id": "a8c0acb7",
        "minute": "55",
        "team": "home"
      },
      {
        "type": "card",
        "card_type": "yellow",
        "player_name": "Carlos Forbs",
        "player_id": "8a310070",
        "minute": "55",
        "team": "home"
      },
      {
        "type": "card",
        "card_type": "yellow",
        "player_name": "Nélson Semedo",
        "player_id": "d04b94db",
        "minute": "70",
        "team": "home"
      },
      {
        "type": "card",
        "card_type": "yellow",
        "player_name": "Vitaly Janelt",
        "player_id": "8449d35e",
        "minute": "87",
        "team": "home"
      },
      {
        "type": "card",
        "card_type": "yellow",
        "player_name": "Players",
        "player_id": null,
        "minute": "2",
        "team": "home"
      }
    ],
    "substitutions": [
      {
        "type": "substitution",
        "player_name": "André",
        "player_id": "ec604e2c",
        "minute": "57",
        "team": "home",
        "substituted_for": "Hwang Hee-chan"
      },
      {
        "type": "substitution",
        "player_name": "Carlos Forbs",
        "player_id": "8a310070",
        "minute": "68",
        "team": "home",
        "substituted_for": "Gonçalo Guedes"
      },
      {
        "type": "substitution",
        "player_name": "Kevin Schade",
        "player_id": "52afb588",
        "minute": "77",
        "team": "home",
        "substituted_for": "Fabio Carvalho"
      },
      {
        "type": "substitution",
        "player_name": "Christian Nørgaard",
        "player_id": "df0a4c90",
        "minute": "77",
        "team": "home",
        "substituted_for": "Yehor Yarmoliuk"
      },
      {
        "type": "substitution",
        "player_name": "João Gomes",
        "player_id": "8b57ad2c",
        "minute": "77",
        "team": "home",
        "substituted_for": "Jean-Ricner Bellegarde"
      },
      {
        "type": "substitution",
        "player_name": "Mikkel Damsgaard",
        "player_id": "215f3907",
        "minute": "90+2",
        "team": "home",
        "substituted_for": "Yunus Emre Konak"
      },
      {
        "type": "substitution",
        "player_name": "Kristoffer Ajer",
        "player_id": "a8c0acb7",
        "minute": "90+2",
        "team": "home",
        "substituted_for": "Mads Roerslev"
      }
    ],
    "other": []
  },
  "player_stats": {
    "home": [
      {
        "player_name": "Kevin Schade",
        "player_id": "52afb588",
        "jersey_number": 7,
        "position": "FW",
        "minutes": 76,
        "goals": 0,
        "assists": 0,
        "shots": 2,
        "shots_on_target": 2,
        "passes": 9,
        "pass_accuracy": 55.6,
        "tackles": 2,
        "interceptions": 0,
        "fouls": null,
        "cards": null
      },
      {
        "player_name": "Fabio Carvalho",
        "player_id": "966e28d0",
        "jersey_number": 14,
        "position": "LW",
        "minutes": 14,
        "goals": 1,
        "assists": 0,
        "shots": 1,
        "shots_on_target": 1,
        "passes": 8,
        "pass_accuracy": 62.5,
        "tackles": 0,
        "interceptions": 0,
        "fouls": null,
        "cards": null
      },
      {
        "player_name": "Keane Lewis-Potter",
        "player_id": "41f08ac8",
        "jersey_number": 23,
        "position": "LW,RW",
        "minutes": 90,
        "goals": 0,
        "assists": 0,
        "shots": 1,
        "shots_on_target": 1,
        "passes": 31,
        "pass_accuracy": 71.0,
        "tackles": 5,
        "interceptions": 0,
        "fouls": null,
        "cards": null
      },
      {
        "player_name": "Bryan Mbeumo",
        "player_id": "6afaebf2",
        "jersey_number": 19,
        "position": "RW,FW",
        "minutes": 90,
        "goals": 1,
        "assists": 0,
        "shots": 1,
        "shots_on_target": 0,
        "passes": 35,
        "pass_accuracy": 80.0,
        "tackles": 2,
        "interceptions": 0,
        "fouls": null,
        "cards": null
      },
      {
        "player_name": "Mikkel Damsgaard",
        "player_id": "215f3907",
        "jersey_number": 24,
        "position": "AM,RM",
        "minutes": 89,
        "goals": 0,
        "assists": 2,
        "shots": 0,
        "shots_on_target": 0,
        "passes": 39,
        "pass_accuracy": 71.8,
        "tackles": 3,
        "interceptions": 0,
        "fouls": null,
        "cards": null
      },
      {
        "player_name": "Yunus Emre Konak",
        "player_id": "e02b5b36",
        "jersey_number": 26,
        "position": "RM",
        "minutes": 1,
        "goals": 0,
        "assists": 0,
        "shots": 1,
        "shots_on_target": 0,
        "passes": 1,
        "pass_accuracy": 100.0,
        "tackles": 0,
        "interceptions": 0,
        "fouls": null,
        "cards": null
      },
      {
        "player_name": "Christian Nørgaard",
        "player_id": "df0a4c90",
        "jersey_number": 6,
        "position": "DM",
        "minutes": 76,
        "goals": 1,
        "assists": 0,
        "shots": 3,
        "shots_on_target": 2,
        "passes": 33,
        "pass_accuracy": 75.8,
        "tackles": 0,
        "interceptions": 1,
        "fouls": null,
        "cards": null
      },
      {
        "player_name": "Yehor Yarmoliuk",
        "player_id": "907a5d7c",
        "jersey_number": 18,
        "position": "LM",
        "minutes": 14,
        "goals": 0,
        "assists": 0,
        "shots": 0,
        "shots_on_target": 0,
        "passes": 10,
        "pass_accuracy": 80.0,
        "tackles": 0,
        "interceptions": 0,
        "fouls": null,
        "cards": null
      },
      {
        "player_name": "Vitaly Janelt",
        "player_id": "8449d35e",
        "jersey_number": 27,
        "position": "DM,CM",
        "minutes": 90,
        "goals": 0,
        "assists": 1,
        "shots": 2,
        "shots_on_target": 1,
        "passes": 34,
        "pass_accuracy": 82.4,
        "tackles": 1,
        "interceptions": 0,
        "fouls": null,
        "cards": "1 yellow"
      },
      {
        "player_name": "Kristoffer Ajer",
        "player_id": "a8c0acb7",
        "jersey_number": 20,
        "position": "LB",
        "minutes": 89,
        "goals": 0,
        "assists": 0,
        "shots": 0,
        "shots_on_target": 0,
        "passes": 29,
        "pass_accuracy": 72.4,
        "tackles": 1,
        "interceptions": 2,
        "fouls": null,
        "cards": "1 yellow"
      },
      {
        "player_name": "Mads Roerslev",
        "player_id": "57c94db2",
        "jersey_number": 30,
        "position": "LB",
        "minutes": 1,
        "goals": 0,
        "assists": 0,
        "shots": 0,
        "shots_on_target": 0,
        "passes": 0,
        "pass_accuracy": null,
        "tackles": 0,
        "interceptions": 0,
        "fouls": null,
        "cards": null
      },
      {
        "player_name": "Ethan Pinnock",
        "player_id": "e541326e",
        "jersey_number": 5,
        "position": "CB",
        "minutes": 90,
        "goals": 1,
        "assists": 0,
        "shots": 3,
        "shots_on_target": 2,
        "passes": 35,
        "pass_accuracy": 71.4,
        "tackles": 2,
        "interceptions": 2,
        "fouls": null,
        "cards": null
      },
      {
        "player_name": "Nathan Collins",
        "player_id": "a8c19eb8",
        "jersey_number": 22,
        "position": "CB",
        "minutes": 90,
        "goals": 1,
        "assists": 0,
        "shots": 2,
        "shots_on_target": 1,
        "passes": 60,
        "pass_accuracy": 76.7,
        "tackles": 0,
        "interceptions": 1,
        "fouls": null,
        "cards": null
      },
      {
        "player_name": "Sepp van den Berg",
        "player_id": "7bf9400b",
        "jersey_number": 4,
        "position": "RB",
        "minutes": 90,
        "goals": 0,
        "assists": 0,
        "shots": 2,
        "shots_on_target": 1,
        "passes": 40,
        "pass_accuracy": 80.0,
        "tackles": 0,
        "interceptions": 0,
        "fouls": null,
        "cards": null
      },
      {
        "player_name": "Mark Flekken",
        "player_id": "a92ab7be",
        "jersey_number": 1,
        "position": "GK",
        "minutes": 90,
        "goals": 0,
        "assists": 0,
        "shots": 0,
        "shots_on_target": 0,
        "passes": 46,
        "pass_accuracy": 73.9,
        "tackles": 0,
        "interceptions": 0,
        "fouls": null,
        "cards": null
      }
    ],
    "away": [
      {
        "player_name": "Jørgen Strand Larsen",
        "player_id": "f553b2b3",
        "jersey_number": 9,
        "position": "FW",
        "minutes": 90,
        "goals": 1,
        "assists": 0,
        "shots": 1,
        "shots_on_target": 1,
        "passes": 13,
        "pass_accuracy": 53.8,
        "tackles": 1,
        "interceptions": 0,
        "fouls": null,
        "cards": null
      },
      {
        "player_name": "Matheus Cunha",
        "player_id": "dc62b55d",
        "jersey_number": 10,
        "position": "LM",
        "minutes": 90,
        "goals": 1,
        "assists": 0,
        "shots": 5,
        "shots_on_target": 1,
        "passes": 44,
        "pass_accuracy": 63.6,
        "tackles": 2,
        "interceptions": 1,
        "fouls": null,
        "cards": null
      },
      {
        "player_name": "João Gomes",
        "player_id": "8b57ad2c",
        "jersey_number": 8,
        "position": "CM",
        "minutes": 76,
        "goals": 0,
        "assists": 0,
        "shots": 1,
        "shots_on_target": 0,
        "passes": 44,
        "pass_accuracy": 77.3,
        "tackles": 2,
        "interceptions": 0,
        "fouls": null,
        "cards": null
      },
      {
        "player_name": "Jean-Ricner Bellegarde",
        "player_id": "10f0fdd3",
        "jersey_number": 27,
        "position": "CM",
        "minutes": 14,
        "goals": 0,
        "assists": 1,
        "shots": 0,
        "shots_on_target": 0,
        "passes": 6,
        "pass_accuracy": 50.0,
        "tackles": 0,
        "interceptions": 0,
        "fouls": null,
        "cards": null
      },
      {
        "player_name": "Mario Lemina",
        "player_id": "2b471f99",
        "jersey_number": 5,
        "position": "CM",
        "minutes": 90,
        "goals": 0,
        "assists": 0,
        "shots": 4,
        "shots_on_target": 1,
        "passes": 36,
        "pass_accuracy": 77.8,
        "tackles": 2,
        "interceptions": 2,
        "fouls": null,
        "cards": null
      },
      {
        "player_name": "Carlos Forbs",
        "player_id": "8a310070",
        "jersey_number": 26,
        "position": "RM",
        "minutes": 67,
        "goals": 0,
        "assists": 0,
        "shots": 0,
        "shots_on_target": 0,
        "passes": 20,
        "pass_accuracy": 80.0,
        "tackles": 4,
        "interceptions": 0,
        "fouls": null,
        "cards": "1 yellow"
      },
      {
        "player_name": "Gonçalo Guedes",
        "player_id": "e6bc67d7",
        "jersey_number": 29,
        "position": "RM",
        "minutes": 23,
        "goals": 0,
        "assists": 0,
        "shots": 1,
        "shots_on_target": 0,
        "passes": 10,
        "pass_accuracy": 80.0,
        "tackles": 1,
        "interceptions": 0,
        "fouls": null,
        "cards": null
      },
      {
        "player_name": "André",
        "player_id": "ec604e2c",
        "jersey_number": 7,
        "position": "DM",
        "minutes": 56,
        "goals": 0,
        "assists": 0,
        "shots": 1,
        "shots_on_target": 1,
        "passes": 38,
        "pass_accuracy": 92.1,
        "tackles": 1,
        "interceptions": 0,
        "fouls": null,
        "cards": null
      },
      {
        "player_name": "Hwang Hee-chan",
        "player_id": "169fd162",
        "jersey_number": 11,
        "position": "DM",
        "minutes": 34,
        "goals": 0,
        "assists": 0,
        "shots": 0,
        "shots_on_target": 0,
        "passes": 9,
        "pass_accuracy": 77.8,
        "tackles": 0,
        "interceptions": 0,
        "fouls": null,
        "cards": null
      },
      {
        "player_name": "Rayan Aït-Nouri",
        "player_id": "9b398aea",
        "jersey_number": 3,
        "position": "LB",
        "minutes": 90,
        "goals": 1,
        "assists": 1,
        "shots": 1,
        "shots_on_target": 1,
        "passes": 61,
        "pass_accuracy": 78.7,
        "tackles": 1,
        "interceptions": 2,
        "fouls": null,
        "cards": null
      },
      {
        "player_name": "Toti Gomes",
        "player_id": "f0caab96",
        "jersey_number": 24,
        "position": "CB",
        "minutes": 90,
        "goals": 0,
        "assists": 0,
        "shots": 1,
        "shots_on_target": 0,
        "passes": 63,
        "pass_accuracy": 77.8,
        "tackles": 2,
        "interceptions": 0,
        "fouls": null,
        "cards": null
      },
      {
        "player_name": "Craig Dawson",
        "player_id": "3e9e06cb",
        "jersey_number": 15,
        "position": "CB",
        "minutes": 90,
        "goals": 0,
        "assists": 0,
        "shots": 1,
        "shots_on_target": 1,
        "passes": 57,
        "pass_accuracy": 84.2,
        "tackles": 1,
        "interceptions": 0,
        "fouls": null,
        "cards": "1 yellow"
      },
      {
        "player_name": "Nélson Semedo",
        "player_id": "d04b94db",
        "jersey_number": 22,
        "position": "RB",
        "minutes": 90,
        "goals": 0,
        "assists": 1,
        "shots": 1,
        "shots_on_target": 0,
        "passes": 64,
        "pass_accuracy": 87.5,
        "tackles": 0,
        "interceptions": 0,
        "fouls": null,
        "cards": "1 yellow"
      },
      {
        "player_name": "Sam Johnstone",
        "player_id": "9e5708be",
        "jersey_number": 31,
        "position": "GK",
        "minutes": 90,
        "goals": 0,
        "assists": 0,
        "shots": 0,
        "shots_on_target": 0,
        "passes": 49,
        "pass_accuracy": 55.1,
        "tackles": 0,
        "interceptions": 0,
        "fouls": null,
        "cards": null
      }
    ]
  },
  "team_stats": {
    "home": {
      "possession": 44.0,
      "passes_completed": 308,
      "passes_attempted": 410,
      "passing_accuracy": 75.0,
      "shots": 18,
      "shots_on_target": 11,
      "saves": 3,
      "fouls": 9,
      "corners": 10,
      "crosses": 27,
      "touches": 538,
      "tackles": 16,
      "interceptions": 6,
      "aerials_won": 22,
      "clearances": 31,
      "offsides": 5,
      "goal_kicks": 10,
      "throw_ins": 11,
      "long_balls": 73,
      "yellow_cards": 2,
      "red_cards": 0
    },
    "away": {
      "possession": 56.0,
      "passes_completed": 394,
      "passes_attempted": 514,
      "passing_accuracy": 77.0,
      "shots": 17,
      "shots_on_target": 6,
      "saves": 7,
      "fouls": 10,
      "corners": 3,
      "crosses": 20,
      "touches": 626,
      "tackles": 17,
      "interceptions": 5,
      "aerials_won": 20,
      "clearances": 24,
      "offsides": 1,
      "goal_kicks": 10,
      "throw_ins": 12,
      "long_balls": 74,
      "yellow_cards": 3,
      "red_cards": 0
    }
  },
  "date": "October 5, 2024"
}